[
  {
    "title": "Lancement du site officiel Firebase",
    "date": "2025-07-23",
    "content": "Le portail Sentinel Vanguard Ai Pro est d\u00e9sormais en ligne : https://sentinel-vanguard-ai-pro.web.app"
  },
  {
    "title": "Int\u00e9gration des modules IA dynamiques",
    "date": "2025-07-22",
    "content": "Ajout des modules IA : pr\u00e9diction comportementale, OSINT g\u00e9olocalis\u00e9, Quantum Shield."
  },
  {
    "title": "D\u00e9ploiement du design immersif",
    "date": "2025-07-21",
    "content": "Interface immersive : globe holographique \ud83c\udf0d, bouclier Sentinel \ud83d\udee1\ufe0f, IA humano\u00efde."
  },
  {
    "title": "Modules \u00e0 venir",
    "date": "\u00c0 venir",
    "content": "Comparateur d\u2019identit\u00e9s, surveillance proactive 24/7, plugin entreprise & mobile."
  }
]